{
	"episode": {
		"number": 38,
		"title": "酒が飲めない ~でも、朝までいる~",
		"titleLines": [
			"酒が飲めない",
			"~でも、朝までいる~"
		],
		"date": "2024年5月5日"
	},
	"bg": "sky",
	"clipStart": 364.1,
	"clipEnd": 409.72,
	"note": "find-highlights候補3位(6:13〜6:43、score=0.1309で5候補中最高)を採用。「みんな無理して飲んでる？」「辛さにシラフで向き合う俺たち」というエピソード説明文の見出しをそのまま回収する本編で、外部文脈なしで単体完結する。冒頭『無理して。みんなあれなんじゃないの。』が強いフックになり、michiruの相槌『間違いない。』が2度目=単独ページで特大表示され締まる。文字起こし校正: 家庭→過程(「かてい」の同音誤認識、酒を正当化する『過程』の意味で家庭は文脈上不成立)、句読点・読点を補完。397.1〜399.3s付近はWhisperが『できないのも』『それたら』を重複・ゼロ長で誤検出したハルシネーション区間のため、LISTENの文字起こし(その手札がないから。忘れられないもん。やったら頭痛くなるだけなんだよ。)を正として整形。話者はLISTEN話者分離を第一ソースとし(0=michiru/1=upamuneの対応は、0が『うぱさんも』と第三者的にupamuneを呼ぶ発話をしている点、および全編8サンプルのF0中央値比較(spk0中央値≈146Hz→michiru167Hzに近い/spk1中央値≈98.6Hz→upamune115Hzに近い、mac版librosa pyinで検証)の両方で一致)、この窓では上記の意味でmichiru=正当化とダメ押しの合いの手、upamune=酔いたいだけ論とシラフの辛さの長い持論、という役割分担。",
	"pages": [
		{
			"start": 364.3,
			"end": 367.62,
			"lines": [
				[
					{ "text": "無理して。", "start": 364.3, "end": 364.98 },
					{ "text": "みんな", "start": 364.98, "end": 365.76 }
				],
				[
					{ "text": "あれなん", "start": 365.76, "end": 366.2 },
					{ "text": "じゃないの。", "start": 366.2, "end": 366.62 }
				]
			],
			"speaker": "upamune"
		},
		{
			"start": 367.62,
			"end": 369.72,
			"lines": [
				[
					{ "text": "この", "start": 367.62, "end": 367.98 },
					{ "text": "お酒", "start": 367.98, "end": 368.32 },
					{ "text": "美味しい、", "start": 368.32, "end": 368.7 }
				],
				[
					{ "text": "ビールうまい", "start": 368.7, "end": 369.28 },
					{ "text": "っていうのは", "start": 369.28, "end": 369.72 }
				]
			],
			"speaker": "upamune"
		},
		{
			"start": 369.72,
			"end": 371.86,
			"lines": [
				[
					{ "text": "ただの", "start": 369.72, "end": 370.3 },
					{ "text": "過程", "start": 370.3, "end": 370.62 },
					{ "text": "であって、", "start": 370.62, "end": 371.2 }
				]
			],
			"speaker": "upamune"
		},
		{
			"start": 371.86,
			"end": 373.78,
			"lines": [
				[
					{ "text": "酔った", "start": 371.86, "end": 372.38 },
					{ "text": "状態", "start": 372.38, "end": 372.82 }
				],
				[
					{ "text": "にな", "start": 372.82, "end": 373.22 },
					{ "text": "りたい", "start": 373.22, "end": 373.5 }
				],
				[
					{ "text": "んじゃない", "start": 373.5, "end": 373.7 },
					{ "text": "ですか。", "start": 373.7, "end": 373.78 }
				]
			],
			"speaker": "upamune"
		},
		{
			"start": 373.78,
			"end": 376.08,
			"lines": [
				[
					{ "text": "それを", "start": 373.78, "end": 374.0 },
					{ "text": "正当化", "start": 374.0, "end": 374.44 },
					{ "text": "するために", "start": 374.44, "end": 375.06 }
				],
				[
					{ "text": "これが", "start": 375.06, "end": 375.62 },
					{ "text": "美味しいから、", "start": 375.62, "end": 376.08 }
				]
			],
			"speaker": "michiru"
		},
		{
			"start": 376.08,
			"end": 378.48,
			"lines": [
				[
					{ "text": "これね、", "start": 376.08, "end": 376.3 },
					{ "text": "美味しい", "start": 376.3, "end": 376.74 },
					{ "text": "んだよね", "start": 376.74, "end": 377.08 }
				],
				[
					{ "text": "飲まざるを", "start": 377.08, "end": 377.66 },
					{ "text": "得ない", "start": 377.66, "end": 377.9 }
				],
				[
					{ "text": "っていう", "start": 377.9, "end": 378.14 },
					{ "text": "風に", "start": 378.14, "end": 378.48 }
				]
			],
			"speaker": "michiru"
		},
		{
			"start": 378.48,
			"end": 380.1,
			"lines": [
				[
					{ "text": "自分を", "start": 378.48, "end": 379.08 },
					{ "text": "納得さ", "start": 379.08, "end": 379.54 },
					{ "text": "せている。", "start": 379.54, "end": 380.1 }
				]
			],
			"speaker": "michiru"
		},
		{
			"start": 380.1,
			"end": 384.26,
			"lines": [
				[
					{ "text": "そう、", "start": 380.1, "end": 380.32 },
					{ "text": "みんな", "start": 380.32, "end": 380.86 },
					{ "text": "辛いんだよ", "start": 380.86, "end": 381.42 }
				],
				[
					{ "text": "その", "start": 381.42, "end": 381.62 },
					{ "text": "シラフで", "start": 381.62, "end": 382.06 }
				],
				[
					{ "text": "生きて", "start": 382.06, "end": 382.26 },
					{ "text": "いくのが", "start": 382.26, "end": 382.66 }
				]
			],
			"speaker": "upamune"
		},
		{
			"start": 384.26,
			"end": 385.66,
			"lines": [
				[
					{ "text": "いやそうなん、", "start": 384.26, "end": 385.02 }
				],
				[
					{ "text": "いや", "start": 385.02, "end": 385.38 },
					{ "text": "そうですね。", "start": 385.38, "end": 385.66 }
				]
			],
			"speaker": "upamune"
		},
		{
			"start": 385.66,
			"end": 390.74,
			"lines": [
				[
					{ "text": "そう", "start": 385.66, "end": 385.78 },
					{ "text": "考えると", "start": 385.78, "end": 386.28 }
				],
				[
					{ "text": "俺たち", "start": 386.28, "end": 386.68 },
					{ "text": "だいぶ", "start": 386.68, "end": 387.08 }
				],
				[
					{ "text": "正直に", "start": 387.08, "end": 388.34 },
					{ "text": "生きちゃう", "start": 388.34, "end": 388.8 }
				]
			],
			"speaker": "upamune"
		},
		{
			"start": 390.74,
			"end": 393.62,
			"lines": [
				[
					{ "text": "辛さと", "start": 390.74, "end": 391.44 },
					{ "text": "真正面から", "start": 391.44, "end": 392.2 }
				],
				[
					{ "text": "付き合ってる。", "start": 392.2, "end": 393.14 }
				]
			],
			"speaker": "upamune"
		},
		{
			"start": 393.62,
			"end": 394.96,
			"lines": [
				[
					{ "text": "そうですよね、", "start": 393.62, "end": 394.06 }
				],
				[
					{ "text": "でも", "start": 394.06, "end": 394.2 },
					{ "text": "忘れたいから", "start": 394.2, "end": 394.96 }
				]
			],
			"speaker": "upamune"
		},
		{
			"start": 394.96,
			"end": 396.54,
			"lines": [
				[
					{ "text": "お酒", "start": 394.96, "end": 395.64 },
					{ "text": "飲んで", "start": 395.64, "end": 395.86 }
				],
				[
					{ "text": "忘れよう", "start": 395.86, "end": 396.2 },
					{ "text": "みたいなのも", "start": 396.2, "end": 396.54 }
				]
			],
			"speaker": "upamune"
		},
		{
			"start": 396.54,
			"end": 398.2,
			"lines": [
				[
					{ "text": "できないのも、", "start": 396.54, "end": 397.1 }
				],
				[
					{ "text": "その", "start": 397.32, "end": 397.54 },
					{ "text": "手札が", "start": 397.54, "end": 397.94 },
					{ "text": "ないから。", "start": 397.94, "end": 398.2 }
				]
			],
			"speaker": "upamune"
		},
		{
			"start": 398.2,
			"end": 401.24,
			"lines": [
				[
					{ "text": "そう", "start": 398.2, "end": 398.42 },
					{ "text": "忘れられない", "start": 398.42, "end": 398.92 },
					{ "text": "もん。", "start": 398.92, "end": 399.3 }
				],
				[
					{ "text": "やったら", "start": 399.3, "end": 399.78 }
				],
				[
					{ "text": "頭痛く", "start": 399.78, "end": 400.2 },
					{ "text": "なるだけ", "start": 400.2, "end": 400.76 },
					{ "text": "なんだよ。", "start": 400.76, "end": 401.24 }
				]
			],
			"speaker": "upamune"
		},
		{
			"start": 401.24,
			"end": 404.64,
			"lines": [
				[
					{ "text": "そう", "start": 401.24, "end": 401.68 },
					{ "text": "忘れる", "start": 401.68, "end": 402.38 },
					{ "text": "とこ", "start": 402.38, "end": 402.86 }
				],
				[
					{ "text": "行く", "start": 402.86, "end": 403.14 },
					{ "text": "前に", "start": 403.14, "end": 403.42 }
				],
				[
					{ "text": "気持ち", "start": 403.42, "end": 403.76 },
					{ "text": "悪くなっちゃう", "start": 403.76, "end": 404.44 },
					{ "text": "から。", "start": 404.44, "end": 404.64 }
				]
			],
			"speaker": "michiru"
		},
		{
			"start": 404.64,
			"end": 406.9,
			"lines": [
				[
					{ "text": "間違いない。", "start": 404.64, "end": 405.42 }
				],
				[
					{ "text": "酒を", "start": 405.42, "end": 405.7 },
					{ "text": "飲んだとしても", "start": 405.7, "end": 406.26 }
				],
				[
					{ "text": "忘れられない。", "start": 406.26, "end": 406.9 }
				]
			],
			"speaker": "michiru"
		},
		{
			"start": 406.9,
			"end": 409.72,
			"lines": [
				[
					{ "text": "間違いない。", "start": 406.9, "end": 407.52 }
				]
			],
			"speaker": "michiru"
		}
	]
}
